setup.py
hello_pypi_yue.egg-info/PKG-INFO
hello_pypi_yue.egg-info/SOURCES.txt
hello_pypi_yue.egg-info/dependency_links.txt
hello_pypi_yue.egg-info/entry_points.txt
hello_pypi_yue.egg-info/top_level.txt
say_hello/__init__.py
say_hello/hello.py